mfd_kernel_namespace/__init__.py
mfd_kernel_namespace/exceptions.py
mfd_kernel_namespace/network_namespace.py
mfd_kernel_namespace-1.8.0.dist-info/licenses/AUTHORS.md
mfd_kernel_namespace-1.8.0.dist-info/licenses/LICENSE.md
mfd_kernel_namespace-1.8.0.dist-info/METADATA
mfd_kernel_namespace-1.8.0.dist-info/WHEEL
mfd_kernel_namespace-1.8.0.dist-info/top_level.txt
mfd_kernel_namespace-1.8.0.dist-info/RECORD
