Metadata-Version: 2.4
Name: mfd-kernel-namespace
Version: 1.8.0
Summary: Module to handle kernel namespaces.
Project-URL: Homepage, https://github.com/intel/mfd
Project-URL: Repository, https://github.com/intel/mfd-kernel-namespace
Project-URL: Issues, https://github.com/intel/mfd-kernel-namespace/issues
Project-URL: Changelog, https://github.com/intel/mfd-kernel-namespace/blob/main/CHANGELOG.md
Requires-Python: <3.14,>=3.10
License-File: LICENSE.md
License-File: AUTHORS.md
Dynamic: license-file
